LICENSE
pycudahll/__init__.py
pycudahll/CudaHLL.py
pycudahll/ExactCardinality.py
pycudahll/helpers.py
pycudahll/StandardHLL.py
pycudahll/tempkernel.cpp
pycudahll-0.1.0.dist-info/LICENSE
pycudahll-0.1.0.dist-info/WHEEL
pycudahll-0.1.0.dist-info/METADATA
pycudahll-0.1.0.dist-info/RECORD
