Metadata-Version: 2.1
Name: pycudahll
Version: 0.1.0
Summary: A GPU implementation of HyperLogLog
Home-page: https://github.com/gabemgem/PyCudaHLL
Keywords: cupy,gpu,hll,hyperloglog
Author: Gabe Maayan
Author-email: gabemgem@gmail.com
Requires-Python: >3.10,<3.12
Classifier: Programming Language :: Python :: 3
Classifier: Programming Language :: Python :: 3.11
Requires-Dist: cupy-cuda12x (>=12.0.0,<13.0.0)
Requires-Dist: hyperloglog (>=0.0.14,<0.0.15)
Requires-Dist: numpy (>=1.24.2,<2.0.0)
Requires-Dist: scipy (>=1.10.1,<2.0.0)
Project-URL: Repository, https://github.com/gabemgem/PyCudaHLL
